speedmeter/__init__.py
speedmeter/api/fast_api.py
speedmeter/format/format.py
speedmeter/meters/bandwidth_meter.py
speedmeter-0.0.4.dist-info/LICENSE
speedmeter-0.0.4.dist-info/METADATA
speedmeter-0.0.4.dist-info/WHEEL
speedmeter-0.0.4.dist-info/entry_points.txt
speedmeter-0.0.4.dist-info/top_level.txt
speedmeter-0.0.4.dist-info/RECORD
