Metadata-Version: 2.1
Name: speedmeter
Version: 0.0.4
Summary: tool to check internet speed
License: MIT License
Project-URL: Homepage, https://github.com/gautamajay52/speedmeter
License-File: LICENSE
Requires-Dist: rich
Requires-Dist: requests
